<?xml version="1.0"?>
<opencv_storage>
<stage13>
  <maxWeakCount>13</maxWeakCount>
  <stageThreshold>-1.1378234624862671e+00</stageThreshold>
  <weakClassifiers>
    <_>
      <internalNodes>
        0 -1 18838 1073741495 -1344613448 -1048487439 -42089267
        797702783 -1802101 -1687189324 -270607371</internalNodes>
      <leafValues>
        -5.9342300891876221e-01 7.3208719491958618e-02</leafValues></_>
    <_>
      <internalNodes>
        0 -1 5798 -1347586065 -1358970861 1460138479 -136843052
        178158395 797939887 1871395699 -253914635</internalNodes>
      <leafValues>
        -4.4288048148155212e-01 2.8913775086402893e-01</leafValues></_>
    <_>
      <internalNodes>
        0 -1 14296 -1382068419 -1358990499 -720906801 -556109446
        1004108410 -1962200950 -911563020 -18022588</internalNodes>
      <leafValues>
        -4.6501049399375916e-01 2.7567619085311890e-01</leafValues></_>
    <_>
      <internalNodes>
        0 -1 20535 792199167 -1880227845 -268697755 -285933573
        2147482975 939524095 -671615129 -721553423</internalNodes>
      <leafValues>
        -3.3563640713691711e-01 3.9827466011047363e-01</leafValues></_>
    <_>
      <internalNodes>
        0 -1 13591 1037925725 -1236965221 1082227037 -1739308021
        -1966510308 -788430646 2143911845 800226148</internalNodes>
      <leafValues>
        -5.1894193887710571e-01 2.6248276233673096e-01</leafValues></_>
    <_>
      <internalNodes>
        0 -1 1721 960494495 -426799032 -619326226 -70434331 1924885243
        -375741697 1334330357 2092679413</internalNodes>
      <leafValues>
        -4.0541127324104309e-01 3.6312833428382874e-01</leafValues></_>
    <_>
      <internalNodes>
        0 -1 6326 -363381458 684952925 -598716388 852512109 -1949603298
        1196034073 -75238899 1918235457</internalNodes>
      <leafValues>
        -6.2345284223556519e-01 2.0555748045444489e-01</leafValues></_>
    <_>
      <internalNodes>
        0 -1 18535 -1541651359 -1889718179 -805152963 2053019135
        -74757596 -385286133 -968184124 2062842485</internalNodes>
      <leafValues>
        -5.9060728549957275e-01 2.2263154387474060e-01</leafValues></_>
    <_>
      <internalNodes>
        0 -1 9169 670440247 1665265745 1409356542 -968163198 1258978071
        -347369327 1032807031 1324905301</internalNodes>
      <leafValues>
        -5.8027476072311401e-01 2.3098902404308319e-01</leafValues></_>
    <_>
      <internalNodes>
        0 -1 20347 -258412459 -1311602593 134255389 1275494541
        1208045602 -1098874696 -1087890923 780995115</internalNodes>
      <leafValues>
        -4.6402531862258911e-01 2.9902166128158569e-01</leafValues></_>
    <_>
      <internalNodes>
        0 -1 11456 654117187 -1910533941 -1790716587 -565268269
        -476415941 -1014419415 -563472831 -593954383</internalNodes>
      <leafValues>
        -5.1518034934997559e-01 2.8318494558334351e-01</leafValues></_>
    <_>
      <internalNodes>
        0 -1 11 105807371 -1540516688 544918358 -405478106 -75433827
        -86800373 1603003493 -1124353099</internalNodes>
      <leafValues>
        -4.5006012916564941e-01 3.3652314543724060e-01</leafValues></_>
    <_>
      <internalNodes>
        0 -1 14510 1418973246 -1265106789 562037119 -272891425
        -1819567116 -1198448640 958941743 1779966769</internalNodes>
      <leafValues>
        -4.4156938791275024e-01 3.6171510815620422e-01</leafValues></_></weakClassifiers></stage13>
</opencv_storage>
