<?xml version="1.0"?>
<opencv_storage>
<stage1>
  <maxWeakCount>5</maxWeakCount>
  <stageThreshold>-1.0194523334503174e+00</stageThreshold>
  <weakClassifiers>
    <_>
      <internalNodes>
        0 -1 11483 -1073793025 -1 -942801985 -589825 -337641473
        -341049994 -2097219 -1346884228</internalNodes>
      <leafValues>
        -7.6121461391448975e-01 6.0180997848510742e-01</leafValues></_>
    <_>
      <internalNodes>
        0 -1 10651 796864319 -1610661889 -134531713 -1073775107 -4704257
        -17937 -67281409 -1073987716</internalNodes>
      <leafValues>
        -6.4018219709396362e-01 6.8673110008239746e-01</leafValues></_>
    <_>
      <internalNodes>
        0 -1 10855 100171765 -2301953 -612795681 -69273121 -169869827
        -105260636 -4343859 2145975796</internalNodes>
      <leafValues>
        -7.0977210998535156e-01 5.8837741613388062e-01</leafValues></_>
    <_>
      <internalNodes>
        0 -1 12420 253509109 -1114113 -86018049 -5768193 -1114800131
        -168696857 -1210107393 1073496060</internalNodes>
      <leafValues>
        -7.9104071855545044e-01 5.1248270273208618e-01</leafValues></_>
    <_>
      <internalNodes>
        0 -1 9678 756104543 804721375 -1816420737 -545613219 989530329
        -343284048 -1924565087 704134128</internalNodes>
      <leafValues>
        -7.1891564130783081e-01 6.3157445192337036e-01</leafValues></_></weakClassifiers></stage1>
</opencv_storage>
