<?xml version="1.0"?>
<opencv_storage>
<stage10>
  <maxWeakCount>8</maxWeakCount>
  <stageThreshold>-1.0049469470977783e+00</stageThreshold>
  <weakClassifiers>
    <_>
      <internalNodes>
        0 -1 6379 6.1973698437213898e-02</internalNodes>
      <leafValues>
        -4.4745764136314392e-01 8.2758623361587524e-01</leafValues></_>
    <_>
      <internalNodes>
        0 -1 128430 -1.4797756448388100e-03</internalNodes>
      <leafValues>
        -6.7102849483489990e-01 2.0935918390750885e-01</leafValues></_>
    <_>
      <internalNodes>
        0 -1 168372 -1.7052610637620091e-03</internalNodes>
      <leafValues>
        -7.5089991092681885e-01 2.3088331520557404e-01</leafValues></_>
    <_>
      <internalNodes>
        0 -1 136847 2.8859865851700306e-03</internalNodes>
      <leafValues>
        1.9942107796669006e-01 -7.5718224048614502e-01</leafValues></_>
    <_>
      <internalNodes>
        0 -1 68478 -8.6052343249320984e-03</internalNodes>
      <leafValues>
        -9.7146278619766235e-01 1.2548933923244476e-01</leafValues></_>
    <_>
      <internalNodes>
        0 -1 161552 -2.0603248849511147e-03</internalNodes>
      <leafValues>
        -6.6269832849502563e-01 2.3419795930385590e-01</leafValues></_>
    <_>
      <internalNodes>
        0 -1 170387 -8.2660512998700142e-04</internalNodes>
      <leafValues>
        -8.0986922979354858e-01 1.3572254776954651e-01</leafValues></_>
    <_>
      <internalNodes>
        0 -1 151870 -3.1799485441297293e-04</internalNodes>
      <leafValues>
        -7.1077948808670044e-01 2.1436083316802979e-01</leafValues></_></weakClassifiers></stage10>
</opencv_storage>
