<?xml version="1.0"?>
<opencv_storage>
<stage2>
  <maxWeakCount>6</maxWeakCount>
  <stageThreshold>-1.0528665781021118e+00</stageThreshold>
  <weakClassifiers>
    <_>
      <internalNodes>
        0 -1 41471 2.9456812143325806e-01</internalNodes>
      <leafValues>
        -6.6551727056503296e-01 8.0000001192092896e-01</leafValues></_>
    <_>
      <internalNodes>
        0 -1 2456 5.6800246238708496e-02</internalNodes>
      <leafValues>
        -3.8553547859191895e-01 7.9821515083312988e-01</leafValues></_>
    <_>
      <internalNodes>
        0 -1 56603 3.4454204142093658e-03</internalNodes>
      <leafValues>
        2.9758214950561523e-01 -8.1867760419845581e-01</leafValues></_>
    <_>
      <internalNodes>
        0 -1 82644 1.1412716703489423e-03</internalNodes>
      <leafValues>
        2.3155240714550018e-01 -8.8571125268936157e-01</leafValues></_>
    <_>
      <internalNodes>
        0 -1 82644 -1.0901773348450661e-03</internalNodes>
      <leafValues>
        -7.7134078741073608e-01 2.7781593799591064e-01</leafValues></_>
    <_>
      <internalNodes>
        0 -1 60794 2.1838829852640629e-03</internalNodes>
      <leafValues>
        3.0849930644035339e-01 -7.7875393629074097e-01</leafValues></_></weakClassifiers></stage2>
</opencv_storage>
