<?xml version="1.0"?>
<opencv_storage>
<stage1>
  <maxWeakCount>7</maxWeakCount>
  <stageThreshold>-1.6976197957992554e+00</stageThreshold>
  <weakClassifiers>
    <_>
      <internalNodes>
        0 -1 121656 1.6676259040832520e-01</internalNodes>
      <leafValues>
        -6.5116280317306519e-01 8.2978725433349609e-01</leafValues></_>
    <_>
      <internalNodes>
        0 -1 157092 -1.2749643065035343e-03</internalNodes>
      <leafValues>
        -7.9875701665878296e-01 4.0678283572196960e-01</leafValues></_>
    <_>
      <internalNodes>
        0 -1 4341 1.7271256446838379e-01</internalNodes>
      <leafValues>
        -4.0872454643249512e-01 8.3540081977844238e-01</leafValues></_>
    <_>
      <internalNodes>
        0 -1 232519 3.2251193188130856e-03</internalNodes>
      <leafValues>
        3.4219148755073547e-01 -8.2800799608230591e-01</leafValues></_>
    <_>
      <internalNodes>
        0 -1 290976 -4.6682736137881875e-04</internalNodes>
      <leafValues>
        -9.3497329950332642e-01 2.9937282204627991e-01</leafValues></_>
    <_>
      <internalNodes>
        0 -1 290976 3.1698512611910701e-04</internalNodes>
      <leafValues>
        3.0824139714241028e-01 -7.4094843864440918e-01</leafValues></_>
    <_>
      <internalNodes>
        0 -1 188240 2.4774693883955479e-03</internalNodes>
      <leafValues>
        2.6040866971015930e-01 -8.6431306600570679e-01</leafValues></_></weakClassifiers></stage1>
</opencv_storage>
